{
  "updatedAt": "2026-05-29T18:40:58.475Z",
  "fx": [
    {
      "code": "USD",
      "name": "Dolar",
      "buy": 45.89,
      "sell": 45.9,
      "change": 0.05
    },
    {
      "code": "EUR",
      "name": "Euro",
      "buy": 53.58,
      "sell": 53.61,
      "change": 0.28
    },
    {
      "code": "GRA",
      "name": "Gram Altın",
      "buy": 6729.34,
      "sell": 6730.2,
      "change": 1.49
    },
    {
      "code": "CEYREKALTIN",
      "name": "Çeyrek Altın",
      "buy": 10725.86,
      "sell": 10972.81,
      "change": 0
    },
    {
      "code": "CUMHURIYETALTINI",
      "name": "Cumhuriyet Altını",
      "buy": 44504,
      "sell": 45176,
      "change": -0.56
    }
  ],
  "news": [
    {
      "title": "Hububatta süne alarımı! Bakanlık teknik ekipleri sahaya indi: O bölgede tüm köyler için ilaçlama kararı verildi",
      "url": "https://www.tarimdanhaber.com/hububatta-sune-alarimi-bakanlik-teknik-ekipleri-sahaya-indi-o-bolgede-tum-koyler-icin-ilaclama-karari-verildi",
      "source": "Tarımdan Haber",
      "date": "2026-05-29"
    },
    {
      "title": "Çin’in otonom traktörü Honghu T70 tarlalarda: Tarımda insan gücü tarihe mi karışıyor?",
      "url": "https://www.tarimdanhaber.com/cinin-otonom-traktoru-sosyal-medyada-viral-oldu-tarlalarda-surucusuz-donem-basliyor",
      "source": "Tarımdan Haber",
      "date": "2026-05-29"
    },
    {
      "title": "Sığır eti 971 TL, tavuk 420 TL! Amerika'da etin kilogramı kaç TL? İşte o çarpıcı liste",
      "url": "https://www.tarimdanhaber.com/sigir-eti-971-tl-tavuk-420-tl-amerikada-etin-kilogrami-kac-tl-iste-o-carpici-liste",
      "source": "Tarımdan Haber",
      "date": "2026-05-29"
    },
    {
      "title": "Son gün 5 Temmuz! Tarımsal amaçlı örgütler için kritik süreç başlıyor",
      "url": "https://www.tarimdanhaber.com/son-gun-5-temmuz-tarimsal-amacli-orgutler-icin-kritik-surec-basliyor",
      "source": "Tarımdan Haber",
      "date": "2026-05-29"
    },
    {
      "title": "Konya’da tarımsal afet! AB tescilli Hüyük çileğini dolu vurdu: 18 bin ton ürün yok oldu!",
      "url": "https://www.tarimdanhaber.com/konyada-tarimsal-afet-ab-tescilli-huyuk-cilegini-dolu-vurdu-18-bin-ton-urun-yok-oldu",
      "source": "Tarımdan Haber",
      "date": "2026-05-28"
    },
    {
      "title": "Elde kalan kurbanlıklara \"Prim\" ayarı: Bakanlıktan flaş fiyat kararı!",
      "url": "https://www.tarimdanhaber.com/elde-kalan-kurbanliklara-prim-ayari-bakanliktan-flas-fiyat-karari",
      "source": "Tarımdan Haber",
      "date": "2026-05-28"
    },
    {
      "title": "Bitlis Tarım ve Orman İl Müdürü Ramazan Çolak Kimdir? İşte kariyeri ve hayatı",
      "url": "https://www.tarimdanhaber.com/bitlis-tarim-ve-orman-il-muduru-ramazan-colak-kimdir-iste-kariyeri-ve-hayati",
      "source": "Tarımdan Haber",
      "date": "2026-05-28"
    },
    {
      "title": "Eskişehir Ticaret Borsası'nda ay sonu raporu: Hasat öncesi buğday ve arpa fiyatları ne durumda?",
      "url": "https://www.tarimdanhaber.com/eskisehir-ticaret-borsasinda-ay-sonu-raporu-hasat-oncesi-bugday-ve-arpa-fiyatlari-ne-durumda",
      "source": "Tarımdan Haber",
      "date": "2026-05-27"
    }
  ],
  "commodities": [
    {
      "key": "bugday",
      "name": "Buğday (ekmeklik)",
      "unit": "₺/kg",
      "price": 14.97,
      "change": 0,
      "source": "Edirne TB",
      "date": "2026-05-11"
    },
    {
      "key": "arpa",
      "name": "Arpa",
      "unit": "₺/kg",
      "price": 13.13,
      "change": 0,
      "source": "Edirne TB",
      "date": "2026-03-30"
    },
    {
      "key": "aycicegi",
      "name": "Ayçiçeği (yağlık)",
      "unit": "₺/kg",
      "price": 32.25,
      "change": 0,
      "source": "Edirne TB",
      "date": "2026-05-18"
    },
    {
      "key": "kanola",
      "name": "Kanola",
      "unit": "₺/kg",
      "price": 19.7,
      "change": 0,
      "source": "Manuel (fallback)"
    }
  ],
  "inputs": [
    {
      "key": "motorin",
      "name": "Motorin (mazot)",
      "unit": "₺/lt",
      "price": 68.15,
      "change": 0,
      "source": "ANKARA ort."
    },
    {
      "key": "ure",
      "name": "Üre Gübre",
      "unit": "₺/kg",
      "price": 16.8,
      "change": 0,
      "source": "Manuel"
    },
    {
      "key": "dap",
      "name": "DAP Gübre",
      "unit": "₺/kg",
      "price": 24.5,
      "change": 0,
      "source": "Manuel"
    },
    {
      "key": "as",
      "name": "Amonyum Sülfat",
      "unit": "₺/kg",
      "price": 11.2,
      "change": 0,
      "source": "Manuel"
    }
  ],
  "note": "Borsa: TOBB Edirne TB · mazot: EPDK bayi ort. · gübre/kanola manuel."
}
